biochemical_data_connectors/__init__.py
biochemical_data_connectors/constants.py
biochemical_data_connectors/models.py
biochemical_data_connectors/connectors/__init__.py
biochemical_data_connectors/connectors/ord_connectors.py
biochemical_data_connectors/connectors/bioactive_compounds/__init__.py
biochemical_data_connectors/connectors/bioactive_compounds/base_bioactives_connector.py
biochemical_data_connectors/connectors/bioactive_compounds/bindingdb_bioactives_connector.py
biochemical_data_connectors/connectors/bioactive_compounds/chembl_bioactives_connector.py
biochemical_data_connectors/connectors/bioactive_compounds/iuphar_bioactives_connector.py
biochemical_data_connectors/connectors/bioactive_compounds/pubchem_bioactives_connector.py
biochemical_data_connectors/utils/__init__.py
biochemical_data_connectors/utils/files_utils.py
biochemical_data_connectors/utils/iter_utils.py
biochemical_data_connectors/utils/standardization_utils.py
biochemical_data_connectors/utils/api/__init__.py
biochemical_data_connectors/utils/api/base_api.py
biochemical_data_connectors/utils/api/bindingdb_api.py
biochemical_data_connectors/utils/api/chembl_api.py
biochemical_data_connectors/utils/api/iuphar_api.py
biochemical_data_connectors/utils/api/mappings.py
biochemical_data_connectors/utils/api/pubchem_api.py
biochemical_data_connectors-3.2.2.dist-info/licenses/LICENSE
biochemical_data_connectors-3.2.2.dist-info/METADATA
biochemical_data_connectors-3.2.2.dist-info/WHEEL
biochemical_data_connectors-3.2.2.dist-info/top_level.txt
biochemical_data_connectors-3.2.2.dist-info/RECORD
