Metadata-Version: 2.4
Name: biochemical-data-connectors
Version: 3.2.2
Summary: A Python package to extract chemical, biochemical, and bioactivity data from public databases like ORD, ChEMBL and PubChem.
Author-email: Christopher van den Berg <cvandenberg1105@googlemail.com>
License: MIT License
Project-URL: Repository, https://github.com/your-username/biochemical-data-connectors
Project-URL: Bug Tracker, https://github.com/your-username/biochemical-data-connectors/issues
Keywords: bioinformatics,cheminformatics,drug discovery,chembl,pubchem,bioactivity,api
Classifier: Programming Language :: Python :: 3.10
Classifier: License :: OSI Approved :: MIT License
Classifier: Operating System :: OS Independent
Classifier: Intended Audience :: Science/Research
Requires-Python: >=3.10
License-File: LICENSE
Requires-Dist: chembl-webresource-client~=0.10.9
Requires-Dist: dimorphite_dl~=2.0.1
Requires-Dist: ord-schema~=0.3.99
Requires-Dist: pubchempy~=1.0.4
Requires-Dist: rdkit~=2025.3.2
Requires-Dist: requests~=2.32.4
Dynamic: license-file
